{
"type": "FeatureCollection",
"name": "bizimistasyonlar2",
"crs": { "type": "name", "properties": { "name": "urn:ogc:def:crs:OGC:1.3:CRS84" } },
"features": [
{ "type": "Feature", "properties": { "ISTASYON": "NAKKAŞTEPE" }, "geometry": { "type": "Point", "coordinates": [ 29.039652813720334, 41.031579170576649 ] } },
{ "type": "Feature", "properties": { "ISTASYON": "15 TEMMUZ ŞEHİTLER KÖPRÜSÜ" }, "geometry": { "type": "Point", "coordinates": [ 29.042989211177986, 41.036313203945923 ] } },
{ "type": "Feature", "properties": { "ISTASYON": "KÜPLÜCE" }, "geometry": { "type": "Point", "coordinates": [ 29.054159110106365, 41.03911249496646 ] } },
{ "type": "Feature", "properties": { "ISTASYON": "KİRAZLITEPE" }, "geometry": { "type": "Point", "coordinates": [ 29.06418052726757, 41.037616174891269 ] } },
{ "type": "Feature", "properties": { "ISTASYON": "MEHMET AKİF ERSOY" }, "geometry": { "type": "Point", "coordinates": [ 29.07770138666136, 41.042259381890645 ] } },
{ "type": "Feature", "properties": { "ISTASYON": "GÜZELTEPE" }, "geometry": { "type": "Point", "coordinates": [ 29.076580805930099, 41.048241580370899 ] } },
{ "type": "Feature", "properties": { "ISTASYON": "BAHÇELİEVLER" }, "geometry": { "type": "Point", "coordinates": [ 29.073223215817258, 41.056811842410298 ] } },
{ "type": "Feature", "properties": { "ISTASYON": "RASATHANE" }, "geometry": { "type": "Point", "coordinates": [ 29.066127090169701, 41.063012767656375 ] } },
{ "type": "Feature", "properties": { "ISTASYON": "KÜÇÜKSU" }, "geometry": { "type": "Point", "coordinates": [ 29.069226379244192, 41.079728263150997 ] } },
{ "type": "Feature", "properties": { "ISTASYON": "GÖZTEPE" }, "geometry": { "type": "Point", "coordinates": [ 29.079438872813345, 41.080738580664324 ] } },
{ "type": "Feature", "properties": { "ISTASYON": "MEDİPOL ÜNİVERSİTESİ" }, "geometry": { "type": "Point", "coordinates": [ 29.088474833452185, 41.088904242629326 ] } },
{ "type": "Feature", "properties": { "ISTASYON": "ORHAN VELİ KANIK CADDESİ" }, "geometry": { "type": "Point", "coordinates": [ 29.091284444435406, 41.094645679234517 ] } },
{ "type": "Feature", "properties": { "ISTASYON": "KAVACIK" }, "geometry": { "type": "Point", "coordinates": [ 29.087332992453717, 41.094989695207751 ] } },
{ "type": "Feature", "properties": { "ISTASYON": "ÇUBUKLU" }, "geometry": { "type": "Point", "coordinates": [ 29.083495990884128, 41.106812767904024 ] } },
{ "type": "Feature", "properties": { "ISTASYON": "BEYKOZ SOSYAL TESİSLERİ" }, "geometry": { "type": "Point", "coordinates": [ 29.088945316901178, 41.113891198946902 ] } },
{ "type": "Feature", "properties": { "ISTASYON": "PAŞABAHÇE-İSKELE" }, "geometry": { "type": "Point", "coordinates": [ 29.095466072396405, 41.115844162747813 ] } },
{ "type": "Feature", "properties": { "ISTASYON": "BEYKOZ DEVLET HASTANESİ" }, "geometry": { "type": "Point", "coordinates": [ 29.097784267316932, 41.118058328541579 ] } },
{ "type": "Feature", "properties": { "ISTASYON": "SULTANİYE" }, "geometry": { "type": "Point", "coordinates": [ 29.098720635381515, 41.12425383369709 ] } },
{ "type": "Feature", "properties": { "ISTASYON": "BEYKOZ" }, "geometry": { "type": "Point", "coordinates": [ 29.09140463668092, 41.134578613009857 ] } },
{ "type": "Feature", "properties": { "ISTASYON": "FISTIKAĞACI" }, "geometry": { "type": "Point", "coordinates": [ 29.028876637146425, 41.028078260757709 ] } }
]
}
